[
  {
    "id": 675,
    "verse_number": 6,
    "verse_key": "5:6",
    "hizb_number": 11,
    "rub_el_hizb_number": 43,
    "ruku_number": 87,
    "manzil_number": 2,
    "sajdah_number": null,
    "text_imlaei": "يَا أَيُّهَا الَّذِينَ آمَنُوا إِذَا قُمْتُمْ إِلَى الصَّلَاةِ فَاغْسِلُوا وُجُوهَكُمْ وَأَيْدِيَكُمْ إِلَى الْمَرَافِقِ وَامْسَحُوا بِرُءُوسِكُمْ وَأَرْجُلَكُمْ إِلَى الْكَعْبَيْنِ ۚ وَإِن كُنتُمْ جُنُبًا فَاطَّهَّرُوا ۚ وَإِن كُنتُم مَّرْضَىٰ أَوْ عَلَىٰ سَفَرٍ أَوْ جَاءَ أَحَدٌ مِّنكُم مِّنَ الْغَائِطِ أَوْ لَامَسْتُمُ النِّسَاءَ فَلَمْ تَجِدُوا مَاءً فَتَيَمَّمُوا صَعِيدًا طَيِّبًا فَامْسَحُوا بِوُجُوهِكُمْ وَأَيْدِيكُم مِّنْهُ ۚ مَا يُرِيدُ اللَّهُ لِيَجْعَلَ عَلَيْكُم مِّنْ حَرَجٍ وَلَٰكِن يُرِيدُ لِيُطَهِّرَكُمْ وَلِيُتِمَّ نِعْمَتَهُ عَلَيْكُمْ لَعَلَّكُمْ تَشْكُرُونَ",
    "text_uthmani": "يَـٰٓأَيُّهَا ٱلَّذِينَ ءَامَنُوٓا۟ إِذَا قُمْتُمْ إِلَى ٱلصَّلَوٰةِ فَٱغْسِلُوا۟ وُجُوهَكُمْ وَأَيْدِيَكُمْ إِلَى ٱلْمَرَافِقِ وَٱمْسَحُوا۟ بِرُءُوسِكُمْ وَأَرْجُلَكُمْ إِلَى ٱلْكَعْبَيْنِ ۚ وَإِن كُنتُمْ جُنُبًا فَٱطَّهَّرُوا۟ ۚ وَإِن كُنتُم مَّرْضَىٰٓ أَوْ عَلَىٰ سَفَرٍ أَوْ جَآءَ أَحَدٌ مِّنكُم مِّنَ ٱلْغَآئِطِ أَوْ لَـٰمَسْتُمُ ٱلنِّسَآءَ فَلَمْ تَجِدُوا۟ مَآءً فَتَيَمَّمُوا۟ صَعِيدًا طَيِّبًا فَٱمْسَحُوا۟ بِوُجُوهِكُمْ وَأَيْدِيكُم مِّنْهُ ۚ مَا يُرِيدُ ٱللَّهُ لِيَجْعَلَ عَلَيْكُم مِّنْ حَرَجٍ وَلَـٰكِن يُرِيدُ لِيُطَهِّرَكُمْ وَلِيُتِمَّ نِعْمَتَهُۥ عَلَيْكُمْ لَعَلَّكُمْ تَشْكُرُونَ",
    "code_v2": "ﱁ ﱂ ﱃ ﱄ ﱅ ﱆ ﱇ ﱈ ﱉ ﱊ ﱋ ﱌ ﱍ ﱎ ﱏ ﱐ ﱑ ﱒ ﱓ ﱔ ﱕ ﱖ ﱗ ﱘ ﱙ ﱚ ﱛ ﱜ ﱝ ﱞ ﱟ ﱠ ﱡ ﱢ ﱣ ﱤ ﱥ ﱦ ﱧ ﱨ ﱩ ﱪ ﱫ ﱬ ﱭ ﱮ ﱯ ﱰ ﱱ ﱲ ﱳ ﱴ ﱵ ﱶ ﱷ ﱸ ﱹ ﱺ ﱻ ﱼ ﱽ ﱾ ﱿ ﲀ ﲁ",
    "chapter_id": 5,
    "page_number": 108,
    "juz_number": 6
  },
  {
    "id": 676,
    "verse_number": 7,
    "verse_key": "5:7",
    "hizb_number": 11,
    "rub_el_hizb_number": 43,
    "ruku_number": 87,
    "manzil_number": 2,
    "sajdah_number": null,
    "text_imlaei": "وَاذْكُرُوا نِعْمَةَ اللَّهِ عَلَيْكُمْ وَمِيثَاقَهُ الَّذِي وَاثَقَكُم بِهِ إِذْ قُلْتُمْ سَمِعْنَا وَأَطَعْنَا ۖ وَاتَّقُوا اللَّهَ ۚ إِنَّ اللَّهَ عَلِيمٌ بِذَاتِ الصُّدُورِ",
    "text_uthmani": "وَٱذْكُرُوا۟ نِعْمَةَ ٱللَّهِ عَلَيْكُمْ وَمِيثَـٰقَهُ ٱلَّذِى وَاثَقَكُم بِهِۦٓ إِذْ قُلْتُمْ سَمِعْنَا وَأَطَعْنَا ۖ وَٱتَّقُوا۟ ٱللَّهَ ۚ إِنَّ ٱللَّهَ عَلِيمٌۢ بِذَاتِ ٱلصُّدُورِ",
    "code_v2": "ﲂ ﲃ ﲄ ﲅ ﲆ ﲇ ﲈ ﲉ ﲊ ﲋ ﲌ ﲍ ﲎ ﲏ ﲐ ﲑ ﲒ ﲓ ﲔ ﲕ ﲖ ﲗ",
    "chapter_id": 5,
    "page_number": 108,
    "juz_number": 6
  },
  {
    "id": 677,
    "verse_number": 8,
    "verse_key": "5:8",
    "hizb_number": 11,
    "rub_el_hizb_number": 43,
    "ruku_number": 87,
    "manzil_number": 2,
    "sajdah_number": null,
    "text_imlaei": "يَا أَيُّهَا الَّذِينَ آمَنُوا كُونُوا قَوَّامِينَ لِلَّهِ شُهَدَاءَ بِالْقِسْطِ ۖ وَلَا يَجْرِمَنَّكُمْ شَنَآنُ قَوْمٍ عَلَىٰ أَلَّا تَعْدِلُوا ۚ اعْدِلُوا هُوَ أَقْرَبُ لِلتَّقْوَىٰ ۖ وَاتَّقُوا اللَّهَ ۚ إِنَّ اللَّهَ خَبِيرٌ بِمَا تَعْمَلُونَ",
    "text_uthmani": "يَـٰٓأَيُّهَا ٱلَّذِينَ ءَامَنُوا۟ كُونُوا۟ قَوَّٰمِينَ لِلَّهِ شُهَدَآءَ بِٱلْقِسْطِ ۖ وَلَا يَجْرِمَنَّكُمْ شَنَـَٔانُ قَوْمٍ عَلَىٰٓ أَلَّا تَعْدِلُوا۟ ۚ ٱعْدِلُوا۟ هُوَ أَقْرَبُ لِلتَّقْوَىٰ ۖ وَٱتَّقُوا۟ ٱللَّهَ ۚ إِنَّ ٱللَّهَ خَبِيرٌۢ بِمَا تَعْمَلُونَ",
    "code_v2": "ﲘ ﲙ ﲚ ﲛ ﲜ ﲝ ﲞ ﲟ ﲠ ﲡ ﲢ ﲣ ﲤ ﲥ ﲦ ﲧ ﲨ ﲩ ﲪ ﲫ ﲬ ﲭ ﲮ ﲯ ﲰ ﲱ ﲲ ﲳ ﲴ ﲵ ﲶ",
    "chapter_id": 5,
    "page_number": 108,
    "juz_number": 6
  },
  {
    "id": 678,
    "verse_number": 9,
    "verse_key": "5:9",
    "hizb_number": 11,
    "rub_el_hizb_number": 43,
    "ruku_number": 87,
    "manzil_number": 2,
    "sajdah_number": null,
    "text_imlaei": "وَعَدَ اللَّهُ الَّذِينَ آمَنُوا وَعَمِلُوا الصَّالِحَاتِ ۙ لَهُم مَّغْفِرَةٌ وَأَجْرٌ عَظِيمٌ",
    "text_uthmani": "وَعَدَ ٱللَّهُ ٱلَّذِينَ ءَامَنُوا۟ وَعَمِلُوا۟ ٱلصَّـٰلِحَـٰتِ ۙ لَهُم مَّغْفِرَةٌ وَأَجْرٌ عَظِيمٌ",
    "code_v2": "ﲷ ﲸ ﲹ ﲺ ﲻ ﲼ  ﲽ ﲾ ﲿ ﳀ ﳁ",
    "chapter_id": 5,
    "page_number": 108,
    "juz_number": 6
  }
]