[
  {
    "id": 4032,
    "verse_number": 62,
    "verse_key": "38:62",
    "hizb_number": 46,
    "rub_el_hizb_number": 183,
    "ruku_number": 396,
    "manzil_number": 6,
    "sajdah_number": null,
    "text_imlaei": "وَقَالُوا مَا لَنَا لَا نَرَىٰ رِجَالًا كُنَّا نَعُدُّهُم مِّنَ الْأَشْرَارِ",
    "text_uthmani": "وَقَالُوا۟ مَا لَنَا لَا نَرَىٰ رِجَالًا كُنَّا نَعُدُّهُم مِّنَ ٱلْأَشْرَارِ",
    "code_v2": "ﱁ ﱂ ﱃ ﱄ ﱅ ﱆ ﱇ ﱈ ﱉ ﱊ ﱋ",
    "chapter_id": 38,
    "page_number": 457,
    "juz_number": 23
  },
  {
    "id": 4033,
    "verse_number": 63,
    "verse_key": "38:63",
    "hizb_number": 46,
    "rub_el_hizb_number": 183,
    "ruku_number": 396,
    "manzil_number": 6,
    "sajdah_number": null,
    "text_imlaei": "أَتَّخَذْنَاهُمْ سِخْرِيًّا أَمْ زَاغَتْ عَنْهُمُ الْأَبْصَارُ",
    "text_uthmani": "أَتَّخَذْنَـٰهُمْ سِخْرِيًّا أَمْ زَاغَتْ عَنْهُمُ ٱلْأَبْصَـٰرُ",
    "code_v2": "ﱌ ﱍ ﱎ ﱏ ﱐ ﱑ ﱒ",
    "chapter_id": 38,
    "page_number": 457,
    "juz_number": 23
  },
  {
    "id": 4034,
    "verse_number": 64,
    "verse_key": "38:64",
    "hizb_number": 46,
    "rub_el_hizb_number": 183,
    "ruku_number": 396,
    "manzil_number": 6,
    "sajdah_number": null,
    "text_imlaei": "إِنَّ ذَٰلِكَ لَحَقٌّ تَخَاصُمُ أَهْلِ النَّارِ",
    "text_uthmani": "إِنَّ ذَٰلِكَ لَحَقٌّ تَخَاصُمُ أَهْلِ ٱلنَّارِ",
    "code_v2": "ﱓ ﱔ ﱕ ﱖ ﱗ ﱘ ﱙ",
    "chapter_id": 38,
    "page_number": 457,
    "juz_number": 23
  },
  {
    "id": 4035,
    "verse_number": 65,
    "verse_key": "38:65",
    "hizb_number": 46,
    "rub_el_hizb_number": 183,
    "ruku_number": 397,
    "manzil_number": 6,
    "sajdah_number": null,
    "text_imlaei": "قُلْ إِنَّمَا أَنَا مُنذِرٌ ۖ وَمَا مِنْ إِلَٰهٍ إِلَّا اللَّهُ الْوَاحِدُ الْقَهَّارُ",
    "text_uthmani": "قُلْ إِنَّمَآ أَنَا۠ مُنذِرٌ ۖ وَمَا مِنْ إِلَـٰهٍ إِلَّا ٱللَّهُ ٱلْوَٰحِدُ ٱلْقَهَّارُ",
    "code_v2": "ﱚ ﱛ ﱜ ﱝ ﱞ ﱟ ﱠ ﱡ ﱢ ﱣ ﱤ ﱥ ﱦ",
    "chapter_id": 38,
    "page_number": 457,
    "juz_number": 23
  },
  {
    "id": 4036,
    "verse_number": 66,
    "verse_key": "38:66",
    "hizb_number": 46,
    "rub_el_hizb_number": 183,
    "ruku_number": 397,
    "manzil_number": 6,
    "sajdah_number": null,
    "text_imlaei": "رَبُّ السَّمَاوَاتِ وَالْأَرْضِ وَمَا بَيْنَهُمَا الْعَزِيزُ الْغَفَّارُ",
    "text_uthmani": "رَبُّ ٱلسَّمَـٰوَٰتِ وَٱلْأَرْضِ وَمَا بَيْنَهُمَا ٱلْعَزِيزُ ٱلْغَفَّـٰرُ",
    "code_v2": "ﱧ ﱨ ﱩ ﱪ ﱫ ﱬ ﱭ ﱮ",
    "chapter_id": 38,
    "page_number": 457,
    "juz_number": 23
  },
  {
    "id": 4037,
    "verse_number": 67,
    "verse_key": "38:67",
    "hizb_number": 46,
    "rub_el_hizb_number": 183,
    "ruku_number": 397,
    "manzil_number": 6,
    "sajdah_number": null,
    "text_imlaei": "قُلْ هُوَ نَبَأٌ عَظِيمٌ",
    "text_uthmani": "قُلْ هُوَ نَبَؤٌا۟ عَظِيمٌ",
    "code_v2": "ﱯ ﱰ ﱱ ﱲ ﱳ",
    "chapter_id": 38,
    "page_number": 457,
    "juz_number": 23
  },
  {
    "id": 4038,
    "verse_number": 68,
    "verse_key": "38:68",
    "hizb_number": 46,
    "rub_el_hizb_number": 183,
    "ruku_number": 397,
    "manzil_number": 6,
    "sajdah_number": null,
    "text_imlaei": "أَنتُمْ عَنْهُ مُعْرِضُونَ",
    "text_uthmani": "أَنتُمْ عَنْهُ مُعْرِضُونَ",
    "code_v2": "ﱴ ﱵ ﱶ ﱷ",
    "chapter_id": 38,
    "page_number": 457,
    "juz_number": 23
  },
  {
    "id": 4039,
    "verse_number": 69,
    "verse_key": "38:69",
    "hizb_number": 46,
    "rub_el_hizb_number": 183,
    "ruku_number": 397,
    "manzil_number": 6,
    "sajdah_number": null,
    "text_imlaei": "مَا كَانَ لِيَ مِنْ عِلْمٍ بِالْمَلَإِ الْأَعْلَىٰ إِذْ يَخْتَصِمُونَ",
    "text_uthmani": "مَا كَانَ لِىَ مِنْ عِلْمٍۭ بِٱلْمَلَإِ ٱلْأَعْلَىٰٓ إِذْ يَخْتَصِمُونَ",
    "code_v2": "ﱸ ﱹ ﱺ ﱻ ﱼ ﱽ ﱾ ﱿ ﲀ ﲁ",
    "chapter_id": 38,
    "page_number": 457,
    "juz_number": 23
  },
  {
    "id": 4040,
    "verse_number": 70,
    "verse_key": "38:70",
    "hizb_number": 46,
    "rub_el_hizb_number": 183,
    "ruku_number": 397,
    "manzil_number": 6,
    "sajdah_number": null,
    "text_imlaei": "إِن يُوحَىٰ إِلَيَّ إِلَّا أَنَّمَا أَنَا نَذِيرٌ مُّبِينٌ",
    "text_uthmani": "إِن يُوحَىٰٓ إِلَىَّ إِلَّآ أَنَّمَآ أَنَا۠ نَذِيرٌ مُّبِينٌ",
    "code_v2": "ﲂ ﲃ ﲄ ﲅ ﲆ ﲇ ﲈ ﲉ ﲊ",
    "chapter_id": 38,
    "page_number": 457,
    "juz_number": 23
  },
  {
    "id": 4041,
    "verse_number": 71,
    "verse_key": "38:71",
    "hizb_number": 46,
    "rub_el_hizb_number": 183,
    "ruku_number": 397,
    "manzil_number": 6,
    "sajdah_number": null,
    "text_imlaei": "إِذْ قَالَ رَبُّكَ لِلْمَلَائِكَةِ إِنِّي خَالِقٌ بَشَرًا مِّن طِينٍ",
    "text_uthmani": "إِذْ قَالَ رَبُّكَ لِلْمَلَـٰٓئِكَةِ إِنِّى خَـٰلِقٌۢ بَشَرًا مِّن طِينٍ",
    "code_v2": "ﲋ ﲌ ﲍ ﲎ ﲏ ﲐ ﲑ ﲒ ﲓ ﲔ",
    "chapter_id": 38,
    "page_number": 457,
    "juz_number": 23
  },
  {
    "id": 4042,
    "verse_number": 72,
    "verse_key": "38:72",
    "hizb_number": 46,
    "rub_el_hizb_number": 183,
    "ruku_number": 397,
    "manzil_number": 6,
    "sajdah_number": null,
    "text_imlaei": "فَإِذَا سَوَّيْتُهُ وَنَفَخْتُ فِيهِ مِن رُّوحِي فَقَعُوا لَهُ سَاجِدِينَ",
    "text_uthmani": "فَإِذَا سَوَّيْتُهُۥ وَنَفَخْتُ فِيهِ مِن رُّوحِى فَقَعُوا۟ لَهُۥ سَـٰجِدِينَ",
    "code_v2": "ﲕ ﲖ ﲗ ﲘ ﲙ ﲚ ﲛ ﲜ ﲝ ﲞ",
    "chapter_id": 38,
    "page_number": 457,
    "juz_number": 23
  },
  {
    "id": 4043,
    "verse_number": 73,
    "verse_key": "38:73",
    "hizb_number": 46,
    "rub_el_hizb_number": 183,
    "ruku_number": 397,
    "manzil_number": 6,
    "sajdah_number": null,
    "text_imlaei": "فَسَجَدَ الْمَلَائِكَةُ كُلُّهُمْ أَجْمَعُونَ",
    "text_uthmani": "فَسَجَدَ ٱلْمَلَـٰٓئِكَةُ كُلُّهُمْ أَجْمَعُونَ",
    "code_v2": "ﲟ ﲠ ﲡ ﲢ ﲣ",
    "chapter_id": 38,
    "page_number": 457,
    "juz_number": 23
  },
  {
    "id": 4044,
    "verse_number": 74,
    "verse_key": "38:74",
    "hizb_number": 46,
    "rub_el_hizb_number": 183,
    "ruku_number": 397,
    "manzil_number": 6,
    "sajdah_number": null,
    "text_imlaei": "إِلَّا إِبْلِيسَ اسْتَكْبَرَ وَكَانَ مِنَ الْكَافِرِينَ",
    "text_uthmani": "إِلَّآ إِبْلِيسَ ٱسْتَكْبَرَ وَكَانَ مِنَ ٱلْكَـٰفِرِينَ",
    "code_v2": "ﲤ ﲥ ﲦ ﲧ ﲨ ﲩ ﲪ",
    "chapter_id": 38,
    "page_number": 457,
    "juz_number": 23
  },
  {
    "id": 4045,
    "verse_number": 75,
    "verse_key": "38:75",
    "hizb_number": 46,
    "rub_el_hizb_number": 183,
    "ruku_number": 397,
    "manzil_number": 6,
    "sajdah_number": null,
    "text_imlaei": "قَالَ يَا إِبْلِيسُ مَا مَنَعَكَ أَن تَسْجُدَ لِمَا خَلَقْتُ بِيَدَيَّ ۖ أَسْتَكْبَرْتَ أَمْ كُنتَ مِنَ الْعَالِينَ",
    "text_uthmani": "قَالَ يَـٰٓإِبْلِيسُ مَا مَنَعَكَ أَن تَسْجُدَ لِمَا خَلَقْتُ بِيَدَىَّ ۖ أَسْتَكْبَرْتَ أَمْ كُنتَ مِنَ ٱلْعَالِينَ",
    "code_v2": "ﲫ ﲬ ﲭ ﲮ ﲯ ﲰ ﲱ ﲲ ﲳ ﲴ ﲵ ﲶ ﲷ ﲸ ﲹ ﲺ",
    "chapter_id": 38,
    "page_number": 457,
    "juz_number": 23
  },
  {
    "id": 4046,
    "verse_number": 76,
    "verse_key": "38:76",
    "hizb_number": 46,
    "rub_el_hizb_number": 183,
    "ruku_number": 397,
    "manzil_number": 6,
    "sajdah_number": null,
    "text_imlaei": "قَالَ أَنَا خَيْرٌ مِّنْهُ ۖ خَلَقْتَنِي مِن نَّارٍ وَخَلَقْتَهُ مِن طِينٍ",
    "text_uthmani": "قَالَ أَنَا۠ خَيْرٌ مِّنْهُ ۖ خَلَقْتَنِى مِن نَّارٍ وَخَلَقْتَهُۥ مِن طِينٍ",
    "code_v2": "ﲻ ﲼ ﲽ ﲾ  ﲿ ﳀ ﳁ ﳂ ﳃ ﳄ ﳅ",
    "chapter_id": 38,
    "page_number": 457,
    "juz_number": 23
  },
  {
    "id": 4047,
    "verse_number": 77,
    "verse_key": "38:77",
    "hizb_number": 46,
    "rub_el_hizb_number": 183,
    "ruku_number": 397,
    "manzil_number": 6,
    "sajdah_number": null,
    "text_imlaei": "قَالَ فَاخْرُجْ مِنْهَا فَإِنَّكَ رَجِيمٌ",
    "text_uthmani": "قَالَ فَٱخْرُجْ مِنْهَا فَإِنَّكَ رَجِيمٌ",
    "code_v2": "ﳆ ﳇ ﳈ ﳉ ﳊ ﳋ",
    "chapter_id": 38,
    "page_number": 457,
    "juz_number": 23
  },
  {
    "id": 4048,
    "verse_number": 78,
    "verse_key": "38:78",
    "hizb_number": 46,
    "rub_el_hizb_number": 183,
    "ruku_number": 397,
    "manzil_number": 6,
    "sajdah_number": null,
    "text_imlaei": "وَإِنَّ عَلَيْكَ لَعْنَتِي إِلَىٰ يَوْمِ الدِّينِ",
    "text_uthmani": "وَإِنَّ عَلَيْكَ لَعْنَتِىٓ إِلَىٰ يَوْمِ ٱلدِّينِ",
    "code_v2": "ﳌ ﳍ ﳎ ﳏ ﳐ ﳑ ﳒ",
    "chapter_id": 38,
    "page_number": 457,
    "juz_number": 23
  },
  {
    "id": 4049,
    "verse_number": 79,
    "verse_key": "38:79",
    "hizb_number": 46,
    "rub_el_hizb_number": 183,
    "ruku_number": 397,
    "manzil_number": 6,
    "sajdah_number": null,
    "text_imlaei": "قَالَ رَبِّ فَأَنظِرْنِي إِلَىٰ يَوْمِ يُبْعَثُونَ",
    "text_uthmani": "قَالَ رَبِّ فَأَنظِرْنِىٓ إِلَىٰ يَوْمِ يُبْعَثُونَ",
    "code_v2": "ﳓ ﳔ ﳕ ﳖ ﳗ ﳘ ﳙ",
    "chapter_id": 38,
    "page_number": 457,
    "juz_number": 23
  },
  {
    "id": 4050,
    "verse_number": 80,
    "verse_key": "38:80",
    "hizb_number": 46,
    "rub_el_hizb_number": 183,
    "ruku_number": 397,
    "manzil_number": 6,
    "sajdah_number": null,
    "text_imlaei": "قَالَ فَإِنَّكَ مِنَ الْمُنظَرِينَ",
    "text_uthmani": "قَالَ فَإِنَّكَ مِنَ ٱلْمُنظَرِينَ",
    "code_v2": "ﳚ ﳛ ﳜ ﳝ ﳞ",
    "chapter_id": 38,
    "page_number": 457,
    "juz_number": 23
  },
  {
    "id": 4051,
    "verse_number": 81,
    "verse_key": "38:81",
    "hizb_number": 46,
    "rub_el_hizb_number": 183,
    "ruku_number": 397,
    "manzil_number": 6,
    "sajdah_number": null,
    "text_imlaei": "إِلَىٰ يَوْمِ الْوَقْتِ الْمَعْلُومِ",
    "text_uthmani": "إِلَىٰ يَوْمِ ٱلْوَقْتِ ٱلْمَعْلُومِ",
    "code_v2": "ﳟ ﳠ ﳡ ﳢ ﳣ",
    "chapter_id": 38,
    "page_number": 457,
    "juz_number": 23
  },
  {
    "id": 4052,
    "verse_number": 82,
    "verse_key": "38:82",
    "hizb_number": 46,
    "rub_el_hizb_number": 183,
    "ruku_number": 397,
    "manzil_number": 6,
    "sajdah_number": null,
    "text_imlaei": "قَالَ فَبِعِزَّتِكَ لَأُغْوِيَنَّهُمْ أَجْمَعِينَ",
    "text_uthmani": "قَالَ فَبِعِزَّتِكَ لَأُغْوِيَنَّهُمْ أَجْمَعِينَ",
    "code_v2": "ﳤ ﳥ ﳦ ﳧ ﳨ",
    "chapter_id": 38,
    "page_number": 457,
    "juz_number": 23
  },
  {
    "id": 4053,
    "verse_number": 83,
    "verse_key": "38:83",
    "hizb_number": 46,
    "rub_el_hizb_number": 183,
    "ruku_number": 397,
    "manzil_number": 6,
    "sajdah_number": null,
    "text_imlaei": "إِلَّا عِبَادَكَ مِنْهُمُ الْمُخْلَصِينَ",
    "text_uthmani": "إِلَّا عِبَادَكَ مِنْهُمُ ٱلْمُخْلَصِينَ",
    "code_v2": "ﳩ ﳪ ﳫ ﳬ ﳭ",
    "chapter_id": 38,
    "page_number": 457,
    "juz_number": 23
  }
]