[
  {
    "id": 5883,
    "verse_number": 35,
    "verse_key": "83:35",
    "hizb_number": 59,
    "rub_el_hizb_number": 235,
    "ruku_number": 527,
    "manzil_number": 7,
    "sajdah_number": null,
    "text_imlaei": "عَلَى الْأَرَائِكِ يَنظُرُونَ",
    "text_uthmani": "عَلَى ٱلْأَرَآئِكِ يَنظُرُونَ",
    "code_v2": "ﱈ ﱉ ﱊ ﱋ",
    "chapter_id": 83,
    "page_number": 589,
    "juz_number": 30
  },
  {
    "id": 5884,
    "verse_number": 36,
    "verse_key": "83:36",
    "hizb_number": 59,
    "rub_el_hizb_number": 235,
    "ruku_number": 527,
    "manzil_number": 7,
    "sajdah_number": null,
    "text_imlaei": "هَلْ ثُوِّبَ الْكُفَّارُ مَا كَانُوا يَفْعَلُونَ",
    "text_uthmani": "هَلْ ثُوِّبَ ٱلْكُفَّارُ مَا كَانُوا۟ يَفْعَلُونَ",
    "code_v2": "ﱌ ﱍ ﱎ ﱏ ﱐ ﱑ ﱒ",
    "chapter_id": 83,
    "page_number": 589,
    "juz_number": 30
  },
  {
    "id": 5885,
    "verse_number": 1,
    "verse_key": "84:1",
    "hizb_number": 59,
    "rub_el_hizb_number": 236,
    "ruku_number": 528,
    "manzil_number": 7,
    "sajdah_number": null,
    "text_imlaei": "إِذَا السَّمَاءُ انشَقَّتْ",
    "text_uthmani": " إِذَا ٱلسَّمَآءُ ٱنشَقَّتْ",
    "code_v2": "ﱓ ﱔ ﱕ ﱖ",
    "chapter_id": 84,
    "page_number": 589,
    "juz_number": 30
  },
  {
    "id": 5886,
    "verse_number": 2,
    "verse_key": "84:2",
    "hizb_number": 59,
    "rub_el_hizb_number": 236,
    "ruku_number": 528,
    "manzil_number": 7,
    "sajdah_number": null,
    "text_imlaei": "وَأَذِنَتْ لِرَبِّهَا وَحُقَّتْ",
    "text_uthmani": "وَأَذِنَتْ لِرَبِّهَا وَحُقَّتْ",
    "code_v2": "ﱗ ﱘ ﱙ ﱚ",
    "chapter_id": 84,
    "page_number": 589,
    "juz_number": 30
  },
  {
    "id": 5887,
    "verse_number": 3,
    "verse_key": "84:3",
    "hizb_number": 59,
    "rub_el_hizb_number": 236,
    "ruku_number": 528,
    "manzil_number": 7,
    "sajdah_number": null,
    "text_imlaei": "وَإِذَا الْأَرْضُ مُدَّتْ",
    "text_uthmani": "وَإِذَا ٱلْأَرْضُ مُدَّتْ",
    "code_v2": "ﱛ ﱜ ﱝ ﱞ",
    "chapter_id": 84,
    "page_number": 589,
    "juz_number": 30
  },
  {
    "id": 5888,
    "verse_number": 4,
    "verse_key": "84:4",
    "hizb_number": 59,
    "rub_el_hizb_number": 236,
    "ruku_number": 528,
    "manzil_number": 7,
    "sajdah_number": null,
    "text_imlaei": "وَأَلْقَتْ مَا فِيهَا وَتَخَلَّتْ",
    "text_uthmani": "وَأَلْقَتْ مَا فِيهَا وَتَخَلَّتْ",
    "code_v2": "ﱟ ﱠ ﱡ ﱢ ﱣ",
    "chapter_id": 84,
    "page_number": 589,
    "juz_number": 30
  },
  {
    "id": 5889,
    "verse_number": 5,
    "verse_key": "84:5",
    "hizb_number": 59,
    "rub_el_hizb_number": 236,
    "ruku_number": 528,
    "manzil_number": 7,
    "sajdah_number": null,
    "text_imlaei": "وَأَذِنَتْ لِرَبِّهَا وَحُقَّتْ",
    "text_uthmani": "وَأَذِنَتْ لِرَبِّهَا وَحُقَّتْ",
    "code_v2": "ﱤ ﱥ ﱦ ﱧ",
    "chapter_id": 84,
    "page_number": 589,
    "juz_number": 30
  },
  {
    "id": 5890,
    "verse_number": 6,
    "verse_key": "84:6",
    "hizb_number": 59,
    "rub_el_hizb_number": 236,
    "ruku_number": 528,
    "manzil_number": 7,
    "sajdah_number": null,
    "text_imlaei": "يَا أَيُّهَا الْإِنسَانُ إِنَّكَ كَادِحٌ إِلَىٰ رَبِّكَ كَدْحًا فَمُلَاقِيهِ",
    "text_uthmani": "يَـٰٓأَيُّهَا ٱلْإِنسَـٰنُ إِنَّكَ كَادِحٌ إِلَىٰ رَبِّكَ كَدْحًا فَمُلَـٰقِيهِ",
    "code_v2": "ﱨ ﱩ ﱪ ﱫ ﱬ ﱭ ﱮ ﱯ ﱰ",
    "chapter_id": 84,
    "page_number": 589,
    "juz_number": 30
  },
  {
    "id": 5891,
    "verse_number": 7,
    "verse_key": "84:7",
    "hizb_number": 59,
    "rub_el_hizb_number": 236,
    "ruku_number": 528,
    "manzil_number": 7,
    "sajdah_number": null,
    "text_imlaei": "فَأَمَّا مَنْ أُوتِيَ كِتَابَهُ بِيَمِينِهِ",
    "text_uthmani": "فَأَمَّا مَنْ أُوتِىَ كِتَـٰبَهُۥ بِيَمِينِهِۦ",
    "code_v2": "ﱱ ﱲ ﱳ ﱴ ﱵ ﱶ",
    "chapter_id": 84,
    "page_number": 589,
    "juz_number": 30
  },
  {
    "id": 5892,
    "verse_number": 8,
    "verse_key": "84:8",
    "hizb_number": 59,
    "rub_el_hizb_number": 236,
    "ruku_number": 528,
    "manzil_number": 7,
    "sajdah_number": null,
    "text_imlaei": "فَسَوْفَ يُحَاسَبُ حِسَابًا يَسِيرًا",
    "text_uthmani": "فَسَوْفَ يُحَاسَبُ حِسَابًا يَسِيرًا",
    "code_v2": "ﱷ ﱸ ﱹ ﱺ ﱻ",
    "chapter_id": 84,
    "page_number": 589,
    "juz_number": 30
  },
  {
    "id": 5893,
    "verse_number": 9,
    "verse_key": "84:9",
    "hizb_number": 59,
    "rub_el_hizb_number": 236,
    "ruku_number": 528,
    "manzil_number": 7,
    "sajdah_number": null,
    "text_imlaei": "وَيَنقَلِبُ إِلَىٰ أَهْلِهِ مَسْرُورًا",
    "text_uthmani": "وَيَنقَلِبُ إِلَىٰٓ أَهْلِهِۦ مَسْرُورًا",
    "code_v2": "ﱼ ﱽ ﱾ ﱿ ﲀ",
    "chapter_id": 84,
    "page_number": 589,
    "juz_number": 30
  },
  {
    "id": 5894,
    "verse_number": 10,
    "verse_key": "84:10",
    "hizb_number": 59,
    "rub_el_hizb_number": 236,
    "ruku_number": 528,
    "manzil_number": 7,
    "sajdah_number": null,
    "text_imlaei": "وَأَمَّا مَنْ أُوتِيَ كِتَابَهُ وَرَاءَ ظَهْرِهِ",
    "text_uthmani": "وَأَمَّا مَنْ أُوتِىَ كِتَـٰبَهُۥ وَرَآءَ ظَهْرِهِۦ",
    "code_v2": "ﲁ ﲂ ﲃ ﲄ ﲅ ﲆ ﲇ",
    "chapter_id": 84,
    "page_number": 589,
    "juz_number": 30
  },
  {
    "id": 5895,
    "verse_number": 11,
    "verse_key": "84:11",
    "hizb_number": 59,
    "rub_el_hizb_number": 236,
    "ruku_number": 528,
    "manzil_number": 7,
    "sajdah_number": null,
    "text_imlaei": "فَسَوْفَ يَدْعُو ثُبُورًا",
    "text_uthmani": "فَسَوْفَ يَدْعُوا۟ ثُبُورًا",
    "code_v2": "ﲈ ﲉ ﲊ ﲋ",
    "chapter_id": 84,
    "page_number": 589,
    "juz_number": 30
  },
  {
    "id": 5896,
    "verse_number": 12,
    "verse_key": "84:12",
    "hizb_number": 59,
    "rub_el_hizb_number": 236,
    "ruku_number": 528,
    "manzil_number": 7,
    "sajdah_number": null,
    "text_imlaei": "وَيَصْلَىٰ سَعِيرًا",
    "text_uthmani": "وَيَصْلَىٰ سَعِيرًا",
    "code_v2": "ﲌ ﲍ ﲎ",
    "chapter_id": 84,
    "page_number": 589,
    "juz_number": 30
  },
  {
    "id": 5897,
    "verse_number": 13,
    "verse_key": "84:13",
    "hizb_number": 59,
    "rub_el_hizb_number": 236,
    "ruku_number": 528,
    "manzil_number": 7,
    "sajdah_number": null,
    "text_imlaei": "إِنَّهُ كَانَ فِي أَهْلِهِ مَسْرُورًا",
    "text_uthmani": "إِنَّهُۥ كَانَ فِىٓ أَهْلِهِۦ مَسْرُورًا",
    "code_v2": "ﲏ ﲐ ﲑ ﲒ ﲓ ﲔ",
    "chapter_id": 84,
    "page_number": 589,
    "juz_number": 30
  },
  {
    "id": 5898,
    "verse_number": 14,
    "verse_key": "84:14",
    "hizb_number": 59,
    "rub_el_hizb_number": 236,
    "ruku_number": 528,
    "manzil_number": 7,
    "sajdah_number": null,
    "text_imlaei": "إِنَّهُ ظَنَّ أَن لَّن يَحُورَ",
    "text_uthmani": "إِنَّهُۥ ظَنَّ أَن لَّن يَحُورَ",
    "code_v2": "ﲕ ﲖ ﲗ ﲘ ﲙ ﲚ",
    "chapter_id": 84,
    "page_number": 589,
    "juz_number": 30
  },
  {
    "id": 5899,
    "verse_number": 15,
    "verse_key": "84:15",
    "hizb_number": 59,
    "rub_el_hizb_number": 236,
    "ruku_number": 528,
    "manzil_number": 7,
    "sajdah_number": null,
    "text_imlaei": "بَلَىٰ إِنَّ رَبَّهُ كَانَ بِهِ بَصِيرًا",
    "text_uthmani": "بَلَىٰٓ إِنَّ رَبَّهُۥ كَانَ بِهِۦ بَصِيرًا",
    "code_v2": "ﲛﲜ ﲝ ﲞ ﲟ ﲠ ﲡ ﲢ",
    "chapter_id": 84,
    "page_number": 589,
    "juz_number": 30
  },
  {
    "id": 5900,
    "verse_number": 16,
    "verse_key": "84:16",
    "hizb_number": 59,
    "rub_el_hizb_number": 236,
    "ruku_number": 528,
    "manzil_number": 7,
    "sajdah_number": null,
    "text_imlaei": "فَلَا أُقْسِمُ بِالشَّفَقِ",
    "text_uthmani": "فَلَآ أُقْسِمُ بِٱلشَّفَقِ",
    "code_v2": "ﲣ ﲤ ﲥ ﲦ",
    "chapter_id": 84,
    "page_number": 589,
    "juz_number": 30
  },
  {
    "id": 5901,
    "verse_number": 17,
    "verse_key": "84:17",
    "hizb_number": 59,
    "rub_el_hizb_number": 236,
    "ruku_number": 528,
    "manzil_number": 7,
    "sajdah_number": null,
    "text_imlaei": "وَاللَّيْلِ وَمَا وَسَقَ",
    "text_uthmani": "وَٱلَّيْلِ وَمَا وَسَقَ",
    "code_v2": "ﲧ ﲨ ﲩ ﲪ",
    "chapter_id": 84,
    "page_number": 589,
    "juz_number": 30
  },
  {
    "id": 5902,
    "verse_number": 18,
    "verse_key": "84:18",
    "hizb_number": 59,
    "rub_el_hizb_number": 236,
    "ruku_number": 528,
    "manzil_number": 7,
    "sajdah_number": null,
    "text_imlaei": "وَالْقَمَرِ إِذَا اتَّسَقَ",
    "text_uthmani": "وَٱلْقَمَرِ إِذَا ٱتَّسَقَ",
    "code_v2": "ﲫ ﲬ ﲭ ﲮ",
    "chapter_id": 84,
    "page_number": 589,
    "juz_number": 30
  },
  {
    "id": 5903,
    "verse_number": 19,
    "verse_key": "84:19",
    "hizb_number": 59,
    "rub_el_hizb_number": 236,
    "ruku_number": 528,
    "manzil_number": 7,
    "sajdah_number": null,
    "text_imlaei": "لَتَرْكَبُنَّ طَبَقًا عَن طَبَقٍ",
    "text_uthmani": "لَتَرْكَبُنَّ طَبَقًا عَن طَبَقٍ",
    "code_v2": "ﲯ ﲰ ﲱ ﲲ ﲳ",
    "chapter_id": 84,
    "page_number": 589,
    "juz_number": 30
  },
  {
    "id": 5904,
    "verse_number": 20,
    "verse_key": "84:20",
    "hizb_number": 59,
    "rub_el_hizb_number": 236,
    "ruku_number": 528,
    "manzil_number": 7,
    "sajdah_number": null,
    "text_imlaei": "فَمَا لَهُمْ لَا يُؤْمِنُونَ",
    "text_uthmani": "فَمَا لَهُمْ لَا يُؤْمِنُونَ",
    "code_v2": "ﲴ ﲵ ﲶ ﲷ ﲸ",
    "chapter_id": 84,
    "page_number": 589,
    "juz_number": 30
  },
  {
    "id": 5905,
    "verse_number": 21,
    "verse_key": "84:21",
    "hizb_number": 59,
    "rub_el_hizb_number": 236,
    "ruku_number": 528,
    "manzil_number": 7,
    "sajdah_number": 13,
    "text_imlaei": "وَإِذَا قُرِئَ عَلَيْهِمُ الْقُرْآنُ لَا يَسْجُدُونَ",
    "text_uthmani": "وَإِذَا قُرِئَ عَلَيْهِمُ ٱلْقُرْءَانُ لَا يَسْجُدُونَ ۩",
    "code_v2": "ﲹ ﲺ ﲻ ﲼ ﲽ ﲾﲿ ﳀ ﳁ",
    "chapter_id": 84,
    "page_number": 589,
    "juz_number": 30
  },
  {
    "id": 5906,
    "verse_number": 22,
    "verse_key": "84:22",
    "hizb_number": 59,
    "rub_el_hizb_number": 236,
    "ruku_number": 528,
    "manzil_number": 7,
    "sajdah_number": null,
    "text_imlaei": "بَلِ الَّذِينَ كَفَرُوا يُكَذِّبُونَ",
    "text_uthmani": "بَلِ ٱلَّذِينَ كَفَرُوا۟ يُكَذِّبُونَ",
    "code_v2": "ﳂ ﳃ ﳄ ﳅ ﳆ",
    "chapter_id": 84,
    "page_number": 589,
    "juz_number": 30
  },
  {
    "id": 5907,
    "verse_number": 23,
    "verse_key": "84:23",
    "hizb_number": 59,
    "rub_el_hizb_number": 236,
    "ruku_number": 528,
    "manzil_number": 7,
    "sajdah_number": null,
    "text_imlaei": "وَاللَّهُ أَعْلَمُ بِمَا يُوعُونَ",
    "text_uthmani": "وَٱللَّهُ أَعْلَمُ بِمَا يُوعُونَ",
    "code_v2": "ﳇ ﳈ ﳉ ﳊ ﳋ",
    "chapter_id": 84,
    "page_number": 589,
    "juz_number": 30
  },
  {
    "id": 5908,
    "verse_number": 24,
    "verse_key": "84:24",
    "hizb_number": 59,
    "rub_el_hizb_number": 236,
    "ruku_number": 528,
    "manzil_number": 7,
    "sajdah_number": null,
    "text_imlaei": "فَبَشِّرْهُم بِعَذَابٍ أَلِيمٍ",
    "text_uthmani": "فَبَشِّرْهُم بِعَذَابٍ أَلِيمٍ",
    "code_v2": "ﳌ ﳍ ﳎ ﳏ",
    "chapter_id": 84,
    "page_number": 589,
    "juz_number": 30
  },
  {
    "id": 5909,
    "verse_number": 25,
    "verse_key": "84:25",
    "hizb_number": 59,
    "rub_el_hizb_number": 236,
    "ruku_number": 528,
    "manzil_number": 7,
    "sajdah_number": null,
    "text_imlaei": "إِلَّا الَّذِينَ آمَنُوا وَعَمِلُوا الصَّالِحَاتِ لَهُمْ أَجْرٌ غَيْرُ مَمْنُونٍ",
    "text_uthmani": "إِلَّا ٱلَّذِينَ ءَامَنُوا۟ وَعَمِلُوا۟ ٱلصَّـٰلِحَـٰتِ لَهُمْ أَجْرٌ غَيْرُ مَمْنُونٍۭ",
    "code_v2": "ﱁ ﱂ ﱃ ﱄ ﱅ ﱆ ﱇ ﱈ ﱉ ﱊ",
    "chapter_id": 84,
    "page_number": 589,
    "juz_number": 30
  }
]